README.rst
setup.py
flamegraph/__init__.py
flamegraph/__main__.py
flamegraph/flamegraph.py
flamegraph.egg-info/PKG-INFO
flamegraph.egg-info/SOURCES.txt
flamegraph.egg-info/dependency_links.txt
flamegraph.egg-info/top_level.txt