Metadata-Version: 1.1
Name: flamegraph
Version: 0.1
Summary: Statistical profiler which outputs in format suitable for FlameGraph
Home-page: https://github.com/evanhempel/python-flamegraph
Author: Evan Hempel
Author-email: evanhempel@evanhempel.com
License: UNLICENSE
Keywords: profiler flamegraph
Platform: UNKNOWN
Classifier: Development Status :: 3 - Alpha
Classifier: Environment :: Console
Classifier: Intended Audience :: Developers
Classifier: License :: Public Domain
Classifier: Programming Language :: Python
Classifier: Topic :: Software Development :: Debuggers
